My_LibrarySys/__init__.py
My_LibrarySys/Library_Base/Library_Book_System.py
My_LibrarySys/Library_Base/Library_Person.py
My_LibrarySys/Library_Base/__init__.py
My_LibrarySys/Library_Opera/Data_.py
My_LibrarySys/Library_Opera/Library_.py
My_LibrarySys/Library_Opera/__init__.py
My_LibrarySys-0.1.dist-info/LICENSE.txt
My_LibrarySys-0.1.dist-info/METADATA
My_LibrarySys-0.1.dist-info/WHEEL
My_LibrarySys-0.1.dist-info/top_level.txt
My_LibrarySys-0.1.dist-info/RECORD
