Metadata-Version: 2.1
Name: My-LibrarySys
Version: 0.1
Summary: Library management system
Home-page: https://github.com/KingOfOrikid/DATA533_proj_step3
Author: Yuki Chen and Sylvia Lyu
Author-email: yuxin.yuki.chen@gmail.com
License: MIT
Platform: UNKNOWN
License-File: LICENSE.txt
